aiohttp_apiset/__init__.py
aiohttp_apiset/compat.py
aiohttp_apiset/dispatcher.py
aiohttp_apiset/exceptions.py
aiohttp_apiset/jinja2.py
aiohttp_apiset/middlewares.py
aiohttp_apiset/py.typed
aiohttp_apiset/utils.py
aiohttp_apiset/views.py
aiohttp_apiset/static/swagger-ui/2/index.html
aiohttp_apiset/static/swagger-ui/2/o2c.html
aiohttp_apiset/static/swagger-ui/2/swagger-ui.js
aiohttp_apiset/static/swagger-ui/2/swagger-ui.min.js
aiohttp_apiset/static/swagger-ui/2/css/print.css
aiohttp_apiset/static/swagger-ui/2/css/reset.css
aiohttp_apiset/static/swagger-ui/2/css/screen.css
aiohttp_apiset/static/swagger-ui/2/css/style.css
aiohttp_apiset/static/swagger-ui/2/css/typography.css
aiohttp_apiset/static/swagger-ui/2/fonts/DroidSans-Bold.ttf
aiohttp_apiset/static/swagger-ui/2/fonts/DroidSans.ttf
aiohttp_apiset/static/swagger-ui/2/images/collapse.gif
aiohttp_apiset/static/swagger-ui/2/images/expand.gif
aiohttp_apiset/static/swagger-ui/2/images/explorer_icons.png
aiohttp_apiset/static/swagger-ui/2/images/favicon-16x16.png
aiohttp_apiset/static/swagger-ui/2/images/favicon-32x32.png
aiohttp_apiset/static/swagger-ui/2/images/favicon.ico
aiohttp_apiset/static/swagger-ui/2/images/logo_small.png
aiohttp_apiset/static/swagger-ui/2/images/pet_store_api.png
aiohttp_apiset/static/swagger-ui/2/images/throbber.gif
aiohttp_apiset/static/swagger-ui/2/images/wordnik_api.png
aiohttp_apiset/static/swagger-ui/2/lang/ca.js
aiohttp_apiset/static/swagger-ui/2/lang/el.js
aiohttp_apiset/static/swagger-ui/2/lang/en.js
aiohttp_apiset/static/swagger-ui/2/lang/es.js
aiohttp_apiset/static/swagger-ui/2/lang/fr.js
aiohttp_apiset/static/swagger-ui/2/lang/geo.js
aiohttp_apiset/static/swagger-ui/2/lang/it.js
aiohttp_apiset/static/swagger-ui/2/lang/ja.js
aiohttp_apiset/static/swagger-ui/2/lang/ko-kr.js
aiohttp_apiset/static/swagger-ui/2/lang/pl.js
aiohttp_apiset/static/swagger-ui/2/lang/pt.js
aiohttp_apiset/static/swagger-ui/2/lang/ru.js
aiohttp_apiset/static/swagger-ui/2/lang/tr.js
aiohttp_apiset-0.9.18.dist-info/METADATA
aiohttp_apiset-0.9.18.dist-info/WHEEL
aiohttp_apiset-0.9.18.dist-info/licenses/LICENSE
aiohttp_apiset-0.9.18.dist-info/RECORD
