Metadata-Version: 2.4
Name: aiohttp-apiset
Version: 0.9.18
Summary: Build routes using swagger specification
Project-URL: Homepage, https://github.com/aamalev/aiohttp_apiset/
Project-URL: Documentation, http://aiohttp-apiset.readthedocs.io/en/latest/?badge=latest
Project-URL: Issues, https://github.com/aamalev/aiohttp-apiset/issues
Project-URL: Source, https://github.com/aamalev/aiohttp-apiset
Author-email: Alexander Malev <malev@somedev.ru>
License-Expression: Apache-2.0
License-File: LICENSE
Keywords: aiohttp,apiset
Classifier: Development Status :: 5 - Production/Stable
Classifier: Framework :: AsyncIO
Classifier: Intended Audience :: Developers
Classifier: License :: OSI Approved :: Apache Software License
Classifier: Programming Language :: Python :: 3
Classifier: Programming Language :: Python :: 3 :: Only
Classifier: Programming Language :: Python :: 3.9
Classifier: Programming Language :: Python :: 3.10
Classifier: Programming Language :: Python :: 3.11
Classifier: Programming Language :: Python :: 3.12
Classifier: Programming Language :: Python :: 3.13
Classifier: Programming Language :: Python :: Implementation :: CPython
Classifier: Programming Language :: Python :: Implementation :: PyPy
Classifier: Topic :: Internet :: WWW/HTTP
Requires-Python: >=3.9
Requires-Dist: aiohttp<4,>=3
Requires-Dist: jsonschema
Requires-Dist: pyyaml
Provides-Extra: dev-lint
Requires-Dist: black==23.3.0; extra == 'dev-lint'
Requires-Dist: isort==5.12.0; extra == 'dev-lint'
Requires-Dist: mypy==1.3.0; extra == 'dev-lint'
Requires-Dist: ruff==0.0.270; extra == 'dev-lint'
Requires-Dist: types-jsonschema; extra == 'dev-lint'
Requires-Dist: types-pyyaml; extra == 'dev-lint'
Provides-Extra: dev-test
Requires-Dist: pytest; extra == 'dev-test'
Requires-Dist: pytest-aiohttp<1; extra == 'dev-test'
Requires-Dist: pytest-cov; extra == 'dev-test'
Requires-Dist: pytest-mock; extra == 'dev-test'
Provides-Extra: docs
Requires-Dist: sphinx-rtd-theme; extra == 'docs'
Requires-Dist: sphinx>=1.4.8; extra == 'docs'
Provides-Extra: jinja2
Requires-Dist: aiohttp-jinja2; extra == 'jinja2'
